dffml_model_pytorch/__init__.py
dffml_model_pytorch/pytorch_base.py
dffml_model_pytorch/pytorch_net.py
dffml_model_pytorch/pytorch_pretrained.py
dffml_model_pytorch/version.py
dffml_model_pytorch/utils/__init__.py
dffml_model_pytorch/utils/config.py
dffml_model_pytorch/utils/utils.py
tests/__init__.py
tests/test_pytorchnet.py
tests/test_resnet18.py
dffml_model_pytorch-0.1.0.post0.dist-info/LICENSE
dffml_model_pytorch-0.1.0.post0.dist-info/METADATA
dffml_model_pytorch-0.1.0.post0.dist-info/WHEEL
dffml_model_pytorch-0.1.0.post0.dist-info/entry_points.txt
dffml_model_pytorch-0.1.0.post0.dist-info/top_level.txt
dffml_model_pytorch-0.1.0.post0.dist-info/RECORD
